gimmebio.taxa_ags_normalizer-0.2.0-py3.6-nspkg.pth
gimmebio/taxa_ags_normalizer/__init__.py
gimmebio/taxa_ags_normalizer/cli.py
gimmebio/taxa_ags_normalizer/normalizer.py
gimmebio.taxa_ags_normalizer-0.2.0.dist-info/METADATA
gimmebio.taxa_ags_normalizer-0.2.0.dist-info/RECORD
gimmebio.taxa_ags_normalizer-0.2.0.dist-info/WHEEL
gimmebio.taxa_ags_normalizer-0.2.0.dist-info/namespace_packages.txt
gimmebio.taxa_ags_normalizer-0.2.0.dist-info/top_level.txt
